dead_hosts/launcher/__about__.py
dead_hosts/launcher/__init__.py
dead_hosts/launcher/authorization.py
dead_hosts/launcher/cli.py
dead_hosts/launcher/command.py
dead_hosts/launcher/info_manager.py
dead_hosts/launcher/orchestration.py
dead_hosts/launcher/platform.py
dead_hosts/launcher/data/__init__.py
dead_hosts/launcher/data/docs/__init__.py
dead_hosts/launcher/data/docs/about_dead_hosts.md
dead_hosts/launcher/data/docs/about_pyfunceble.md
dead_hosts/launcher/data/standard/__init__.py
dead_hosts/launcher/data/standard/info.example.json
dead_hosts/launcher/defaults/__init__.py
dead_hosts/launcher/defaults/envs.py
dead_hosts/launcher/defaults/links.py
dead_hosts/launcher/defaults/markers.py
dead_hosts/launcher/defaults/paths.py
dead_hosts/launcher/defaults/pyfunceble.py
dead_hosts/launcher/updater/__init__.py
dead_hosts/launcher/updater/all.py
dead_hosts/launcher/updater/base.py
dead_hosts/launcher/updater/github_actions_workflows.py
dead_hosts/launcher/updater/official_pyfunceble_config.py
dead_hosts/launcher/updater/official_pyfunceble_license.py
dead_hosts/launcher/updater/our_infrastructure.py
dead_hosts/launcher/updater/our_license.py
dead_hosts/launcher/updater/our_requirements.py
dead_hosts/launcher/updater/pyfunceble_config.py
dead_hosts/launcher/updater/pyfunceble_config_location.py
dead_hosts/launcher/updater/readme.py
dead_hosts_launcher-2.4.0.dist-info/licenses/LICENSE
dead_hosts_launcher-2.4.0.dist-info/METADATA
dead_hosts_launcher-2.4.0.dist-info/WHEEL
dead_hosts_launcher-2.4.0.dist-info/entry_points.txt
dead_hosts_launcher-2.4.0.dist-info/top_level.txt
dead_hosts_launcher-2.4.0.dist-info/RECORD
