Metadata-Version: 2.4
Name: dead-hosts-launcher
Version: 2.4.0
Summary: The launcher of the Dead-Hosts infrastructure.
Home-page: https://github.com/dead-hosts/infrastructure-launcher
License: MIT
Keywords: Python,infrastructure,dead-hosts
Platform: any
Classifier: Environment :: Console
Classifier: Topic :: Internet
Classifier: Development Status :: 5 - Production/Stable
Classifier: Intended Audience :: Developers
Classifier: Programming Language :: Python
Classifier: Programming Language :: Python :: 3
Classifier: License :: OSI Approved :: MIT License
License-File: LICENSE
Requires-Dist: requests
Requires-Dist: pyyaml
Requires-Dist: PyFunceble-dev~=4.3.0a1
Dynamic: classifier
Dynamic: description
Dynamic: description-content-type
Dynamic: home-page
Dynamic: keywords
Dynamic: license
Dynamic: license-file
Dynamic: platform
Dynamic: requires-dist
Dynamic: summary
